AUTHORS
COPYING
README.rst
iotlab-plot
plot_oml_consum
plot_oml_radio
plot_oml_traj
setup.cfg
setup.py
oml_plot_tools/__init__.py
oml_plot_tools/common.py
oml_plot_tools/consum.py
oml_plot_tools/main.py
oml_plot_tools/radio.py
oml_plot_tools/traj.py
oml_plot_tools.egg-info/PKG-INFO
oml_plot_tools.egg-info/SOURCES.txt
oml_plot_tools.egg-info/dependency_links.txt
oml_plot_tools.egg-info/requires.txt
oml_plot_tools.egg-info/top_level.txt
oml_plot_tools/tests/__init__.py
oml_plot_tools/tests/common.py
oml_plot_tools/tests/common_test.py
oml_plot_tools/tests/consum_test.py
oml_plot_tools/tests/main_parser_test.py
oml_plot_tools/tests/radio_test.py
oml_plot_tools/tests/traj_test.py