Metadata-Version: 2.1
Name: oml-plot-tools
Version: 0.8.0
Summary: IoT-LAB OML plot tools
Home-page: http://www.iot-lab.info
Author: IoT-LAB Team
Author-email: admin@iot-lab.info
License: CeCILL v2.1
Download-URL: http://github.com/iot-lab/oml-plot-tools/
Platform: UNKNOWN
Classifier: Development Status :: 3 - Alpha
Classifier: Programming Language :: Python
Classifier: Programming Language :: Python :: 3
Classifier: Intended Audience :: End Users/Desktop
Classifier: Environment :: Console
Classifier: Topic :: Utilities
License-File: COPYING
License-File: AUTHORS
